LICENSE.txt
MANIFEST.in
README.md
requirements.txt
setup.cfg
setup.py
s3conf/__init__.py
s3conf/__main__.py
s3conf/client.py
s3conf/config.py
s3conf/exceptions.py
s3conf/patch.py
s3conf/s3conf.py
s3conf/storages.py
s3conf.egg-info/PKG-INFO
s3conf.egg-info/SOURCES.txt
s3conf.egg-info/dependency_links.txt
s3conf.egg-info/entry_points.txt
s3conf.egg-info/requires.txt
s3conf.egg-info/top_level.txt
s3conf/storage/__init__.py
s3conf/storage/exceptions.py
s3conf/storage/files.py
s3conf/storage/storages.py