Metadata-Version: 2.1
Name: s3conf
Version: 0.9.6
Summary: Utility package to help managing configuration files stored in S3-like services.
Home-page: https://github.com/sbneto/s3conf
Author: Samuel Martins Barbosa Neto
Author-email: samuel.m.b.neto@gmail.com
License: MIT
Platform: UNKNOWN
Classifier: Environment :: Web Environment
Classifier: Intended Audience :: Developers
Classifier: Programming Language :: Python :: 3 :: Only
Classifier: Programming Language :: Python :: 3
Classifier: Programming Language :: Python :: 3.5
Classifier: Programming Language :: Python :: 3.6
Classifier: Topic :: Internet
Classifier: Topic :: Software Development :: Libraries :: Python Modules
Requires-Python: >=3.6
Provides-Extra: gcp
Provides-Extra: aws
